tree_diff/main.py
tree_diff-0.0.1.dist-info/METADATA
tree_diff-0.0.1.dist-info/WHEEL
tree_diff-0.0.1.dist-info/entry_points.txt
tree_diff-0.0.1.dist-info/top_level.txt
tree_diff-0.0.1.dist-info/RECORD
